flytekitplugins_flyteinteractive-1.16.12-py3.14-nspkg.pth
flytekitplugins/flyteinteractive/__init__.py
flytekitplugins/flyteinteractive/constants.py
flytekitplugins/flyteinteractive/utils.py
flytekitplugins/flyteinteractive/jupyter_lib/__init__.py
flytekitplugins/flyteinteractive/jupyter_lib/decorator.py
flytekitplugins/flyteinteractive/jupyter_lib/jupyter_constants.py
flytekitplugins/flyteinteractive/vscode_lib/__init__.py
flytekitplugins/flyteinteractive/vscode_lib/config.py
flytekitplugins/flyteinteractive/vscode_lib/decorator.py
flytekitplugins/flyteinteractive/vscode_lib/vscode_constants.py
flytekitplugins_flyteinteractive-1.16.12.dist-info/METADATA
flytekitplugins_flyteinteractive-1.16.12.dist-info/WHEEL
flytekitplugins_flyteinteractive-1.16.12.dist-info/entry_points.txt
flytekitplugins_flyteinteractive-1.16.12.dist-info/namespace_packages.txt
flytekitplugins_flyteinteractive-1.16.12.dist-info/top_level.txt
flytekitplugins_flyteinteractive-1.16.12.dist-info/RECORD
