Metadata-Version: 2.4
Name: flytekitplugins-flyteinteractive
Version: 1.16.12
Summary: This package holds the flyteinteractive plugins for flytekit
Author: flyteorg
Author-email: admin@flyte.org
License: apache2
Classifier: Intended Audience :: Science/Research
Classifier: Intended Audience :: Developers
Classifier: License :: OSI Approved :: Apache Software License
Classifier: Programming Language :: Python :: 3.9
Classifier: Programming Language :: Python :: 3.10
Classifier: Programming Language :: Python :: 3.11
Classifier: Topic :: Scientific/Engineering
Classifier: Topic :: Scientific/Engineering :: Artificial Intelligence
Classifier: Topic :: Software Development
Classifier: Topic :: Software Development :: Libraries
Classifier: Topic :: Software Development :: Libraries :: Python Modules
Requires-Python: >=3.9
Requires-Dist: flytekit<2.0.0,>=1.1.0b0
Requires-Dist: jupyter
Dynamic: author
Dynamic: author-email
Dynamic: classifier
Dynamic: license
Dynamic: requires-dist
Dynamic: requires-python
Dynamic: summary
